ortler/__init__.py
ortler/client.py
ortler/command.py
ortler/log.py
ortler/main.py
ortler/profile.py
ortler/qlever.py
ortler/rdf.py
ortler/utils.py
ortler/commands/__init__.py
ortler/commands/ai_review.py
ortler/commands/dump.py
ortler/commands/invitations.py
ortler/commands/mail.py
ortler/commands/recruitment.py
ortler/commands/submissions.py
ortler/commands/submit.py
ortler/commands/update.py
ortler/commands/users.py
ortler-0.2.9.dist-info/licenses/LICENSE
ortler-0.2.9.dist-info/METADATA
ortler-0.2.9.dist-info/WHEEL
ortler-0.2.9.dist-info/entry_points.txt
ortler-0.2.9.dist-info/top_level.txt
ortler-0.2.9.dist-info/RECORD
