Metadata-Version: 2.4
Name: ortler
Version: 0.2.9
Project-URL: Homepage, https://github.com/ad-freiburg/ortler
Project-URL: Repository, https://github.com/ad-freiburg/ortler
Requires-Python: >=3.10
License-File: LICENSE
Requires-Dist: openreview-py
Requires-Dist: argcomplete
Requires-Dist: numpy
Requires-Dist: openai
Requires-Dist: pdf2image
Requires-Dist: reportlab
Requires-Dist: python-dotenv
Requires-Dist: termcolor
Dynamic: license-file
